swelist/__init__.py
swelist/main.py
swelist-0.1.7.dist-info/licenses/LICENSE
swelist-0.1.7.dist-info/METADATA
swelist-0.1.7.dist-info/WHEEL
swelist-0.1.7.dist-info/entry_points.txt
swelist-0.1.7.dist-info/top_level.txt
swelist-0.1.7.dist-info/RECORD
