Metadata-Version: 2.4
Name: swelist
Version: 0.1.7
Summary: A CLI tool for job seekers
Home-page: https://github.com/chenyuan99/swelist
Author: Yuan Chen
Author-email: yuan.chen@sojoai.com
Classifier: Programming Language :: Python :: 3
Classifier: License :: OSI Approved :: MIT License
Classifier: Operating System :: OS Independent
Requires-Python: >=3.7
License-File: LICENSE
Requires-Dist: typer
Dynamic: author
Dynamic: author-email
Dynamic: classifier
Dynamic: description
Dynamic: description-content-type
Dynamic: home-page
Dynamic: license-file
Dynamic: requires-dist
Dynamic: requires-python
Dynamic: summary
